{
    "3": {
        "name": "三日月宗進"
    },
    "5": {
        "name": "小狐丸"
    },
    "7": {
        "name": "石切丸"
    },
    "8": {
        "name": "石切丸．極"
    },
    "9": {
        "name": "岩融"
    },
    "11": {
        "name": "今剣"
    },
    "12": {
        "name": "今剣．極"
    },
    "13": {
        "name": "大典太光世"
    },
    "15": {
        "name": "ソハヤノツルキ"
    },
    "17": {
        "name": "數珠丸恆次"
    },
    "19": {
        "name": "にっかり青江"
    },
    "20": {
        "name": "にっかり青江．極"
    },
    "23": {
        "name": "鳴狐"
    },
    "24": {
        "name": "鳴狐．極"
    },
    "25": {
        "name": "一期一振"
    },
    "27": {
        "name": "鯰尾藤四郎"
    },
    "28": {
        "name": "鯰尾藤四郎．極"
    },
    "29": {
        "name": "骨喰藤四郎"
    },
    "30": {
        "name": "骨喰藤四郎．極"
    },
    "31": {
        "name": "平野藤四郎"
    },
    "32": {
        "name": "平野藤四郎．極"
    },
    "33": {
        "name": "厚藤四郎"
    },
    "34": {
        "name": "厚藤四郎．極"
    },
    "35": {
        "name": "後藤藤四郎"
    },
    "36": {
        "name": "後藤藤四郎．極"
    },
    "37": {
        "name": "信濃藤四郎"
    },
    "38": {
        "name": "信濃藤四郎．極"
    },
    "39": {
        "name": "前田藤四郎"
    },
    "40": {
        "name": "前田藤四郎．極"
    },
    "41": {
        "name": "秋田藤四郎"
    },
    "42": {
        "name": "秋田藤四郎．極"
    },
    "43": {
        "name": "博多藤四郎"
    },
    "44": {
        "name": "博多藤四郎．極"
    },
    "45": {
        "name": "亂藤四郎"
    },
    "46": {
        "name": "亂藤四郎．極"
    },
    "47": {
        "name": "五虎退"
    },
    "48": {
        "name": "五虎退．極"
    },
    "49": {
        "name": "薬研藤四郎"
    },
    "50": {
        "name": "薬研藤四郎．極"
    },
    "51": {
        "name": "包丁藤四郎"
    },
    "52": {
        "name": "包丁藤四郎．極"
    },
    "53": {
        "name": "大包平"
    },
    "55": {
        "name": "鶯丸"
    },
    "57": {
        "name": "明石国行"
    },
    "59": {
        "name": "蛍丸"
    },
    "60": {
        "name": "蛍丸．極"
    },
    "61": {
        "name": "愛染国俊"
    },
    "62": {
        "name": "愛染国俊．極"
    },
    "63": {
        "name": "千子村正"
    },
    "64": {
        "name": "千子村正"
    },
    "65": {
        "name": "蜻蛉切"
    },
    "67": {
        "name": "物吉貞宗"
    },
    "68": {
        "name": "物吉貞宗．極"
    },
    "69": {
        "name": "太鼓鐘貞宗"
    },
    "70": {
        "name": "太鼓鐘貞宗．極"
    },
    "71": {
        "name": "亀甲貞宗"
    },
    "72": {
        "name": "亀甲貞宗．極"
    },
    "73": {
        "name": "燭台切光忠"
    },
    "75": {
        "name": "大般若長光"
    },
    "77": {
        "name": "小竜景光"
    },
    "79": {
        "name": "江雪左文字"
    },
    "81": {
        "name": "宗三左文字"
    },
    "82": {
        "name": "宗三左文字．極"
    },
    "83": {
        "name": "小夜左文字"
    },
    "84": {
        "name": "小夜左文字．極"
    },
    "85": {
        "name": "加州清光"
    },
    "86": {
        "name": "加州清光．極"
    },
    "87": {
        "name": "大和守安定"
    },
    "88": {
        "name": "大和守安定．極"
    },
    "89": {
        "name": "歌仙兼定"
    },
    "90": {
        "name": "歌仙兼定．極"
    },
    "91": {
        "name": "和泉守兼定"
    },
    "92": {
        "name": "和泉守兼定．極"
    },
    "93": {
        "name": "陸奥守吉行"
    },
    "94": {
        "name": "陸奥守吉行．極"
    },
    "95": {
        "name": "山姥切国広"
    },
    "96": {
        "name": "山姥切国広．極"
    },
    "97": {
        "name": "山伏国広"
    },
    "99": {
        "name": "堀川国広"
    },
    "100": {
        "name": "堀川国広．極"
    },
    "101": {
        "name": "蜂須賀虎徹"
    },
    "102": {
        "name": "蜂須賀虎徹．極"
    },
    "103": {
        "name": "浦島虎徹"
    },
    "104": {
        "name": "浦島虎徹．極"
    },
    "105": {
        "name": "長曽祢虎徹"
    },
    "106": {
        "name": "長曽祢虎徹．極"
    },
    "107": {
        "name": "髭切"
    },
    "108": {
        "name": "髭切"
    },
    "109": {
        "name": "髭切"
    },
    "110": {
        "name": "髭切"
    },
    "112": {
        "name": "膝丸"
    },
    "113": {
        "name": "膝丸"
    },
    "114": {
        "name": "膝丸"
    },
    "116": {
        "name": "大倶利伽羅"
    },
    "117": {
        "name": "大倶利伽羅．極"
    },
    "118": {
        "name": "へし切長谷部"
    },
    "119": {
        "name": "へし切長谷部．極"
    },
    "120": {
        "name": "不動行光"
    },
    "121": {
        "name": "不動行光．極"
    },
    "122": {
        "name": "獅子王"
    },
    "124": {
        "name": "小烏丸"
    },
    "128": {
        "name": "同田貫正国"
    },
    "129": {
        "name": "同田貫正国．極"
    },
    "130": {
        "name": "鶴丸国永"
    },
    "132": {
        "name": "太郎太刀"
    },
    "133": {
        "name": "太郎太刀．極"
    },
    "134": {
        "name": "次郎太刀"
    },
    "135": {
        "name": "次郎太刀．極"
    },
    "136": {
        "name": "日本号"
    },
    "138": {
        "name": "御手杵"
    },
    "140": {
        "name": "巴形薙刀"
    },
    "142": {
        "name": "毛利藤四郎"
    },
    "144": {
        "name": "篭手切江"
    },
    "146": {
        "name": "謙信景光"
    },
    "148": {
        "name": "小豆長光"
    },
    "150": {
        "name": "日向正宗"
    },
    "152": {
        "name": "静形薙刀"
    },
    "154": {
        "name": "南泉一文字"
    },
    "156": {
        "name": "千代金丸"
    },
    "158": {
        "name": "山姥切長義"
    },
    "160": {
        "name": "豊前江"
    },
    "162": {
        "name": "祢々切丸"
    },
    "164": {
        "name": "白山吉光"
    },
    "166": {
        "name": "南海太郎朝尊"
    },
    "168": {
        "name": "肥前忠広"
    },
    "170": {
        "name": "北谷菜切"
    },
    "172": {
        "name": "桑名江"
    },
    "174": {
        "name": "水心子正秀"
    },
    "176": {
        "name": "源清麿"
    },
    "178": {
        "name": "松井江"
    }
}
